llama_index/storage/chat_store/yugabytedb/__init__.py
llama_index/storage/chat_store/yugabytedb/base.py
llama_index_storage_chat_store_yugabytedb-0.1.1.dist-info/METADATA
llama_index_storage_chat_store_yugabytedb-0.1.1.dist-info/WHEEL
llama_index_storage_chat_store_yugabytedb-0.1.1.dist-info/licenses/LICENSE
llama_index_storage_chat_store_yugabytedb-0.1.1.dist-info/RECORD
