Metadata-Version: 2.4
Name: llama-index-storage-chat-store-yugabytedb
Version: 0.1.1
Summary: llama-index storage-chat-store yugabytedb integration
Author-email: YugabyteDB <pypi@yugabyte.com>
License-Expression: MIT
License-File: LICENSE
Requires-Python: <4.0,>=3.9
Requires-Dist: llama-index-core<0.15,>=0.13.0
Requires-Dist: psycopg2-yugabytedb>=2.9.3.5
Requires-Dist: sqlalchemy-yugabytedb>=1.0.0.1
